eval7/__init__.py
eval7/cards.cpython-310-darwin.so
eval7/equity.cpython-310-darwin.so
eval7/evaluate.cpython-310-darwin.so
eval7/handrange.py
eval7/rangestring.py
eval7/xorshift_rand.cpython-310-darwin.so
eval7-0.1.10.dist-info/LICENSE
eval7-0.1.10.dist-info/METADATA
eval7-0.1.10.dist-info/WHEEL
eval7-0.1.10.dist-info/top_level.txt
eval7-0.1.10.dist-info/RECORD
