Metadata-Version: 2.1
Name: eval7
Version: 0.1.10
Summary: A poker hand evaluation and equity calculation library
Home-page: https://github.com/JulianAndrews/pyeval7
License: MIT
Keywords: poker equity library
Platform: UNKNOWN
Classifier: Development Status :: 3 - Alpha
Classifier: Intended Audience :: Developers
Classifier: License :: OSI Approved :: MIT License
Classifier: Programming Language :: Python :: 3.5
Classifier: Programming Language :: Python :: 3.6
Classifier: Programming Language :: Python :: 3.7
Classifier: Programming Language :: Cython
Classifier: Topic :: Software Development :: Libraries
Classifier: Topic :: Games/Entertainment
License-File: LICENSE
Requires-Dist: pyparsing
Requires-Dist: future
